Makefile
build_test.sh
header.txt
setup.py
test.py
testing.ini.gpg
tox.ini
docs/Makefile
docs/make.bat
docs/source/CHANGES.rst
docs/source/README.rst
docs/source/conf.py
docs/source/index.rst
pp/__init__.py
pp.core2.egg-info/PKG-INFO
pp.core2.egg-info/SOURCES.txt
pp.core2.egg-info/dependency_links.txt
pp.core2.egg-info/entry_points.txt
pp.core2.egg-info/namespace_packages.txt
pp.core2.egg-info/not-zip-safe
pp.core2.egg-info/requires.txt
pp.core2.egg-info/top_level.txt
pp/core2/__init__.py
pp/core2/conversion.py
pp/core2/fslayer.py
pp/core2/logger.py
pp/core2/resource.py
pp/core2/resources_registry.py
pp/core2/transformation.py
pp/core2/util.py
pp/core2/samples/demo.html
pp/core2/tests/__init__.py
pp/core2/tests/fs_base.py
pp/core2/tests/test_resource.py
pp/core2/tests/test_resources_registry.py
pp/core2/tests/test_transformation.py
pp/core2/tests/test_util.py
pp/core2/tests/example_resource/demo.css
pp/core2/tests/example_resource/demo.pt
pp/core2/tests/sampledata/1.html
pp/core2/tests/sampledata/2.html
pp/core2/tests/sampledata/3.html