Metadata-Version: 1.1
Name: pp.core2
Version: 0.5.3
Summary: pp.core
Home-page: http://pypi.python.org/pypi/pp.core2
Author: Andreas Jung
Author-email: info@zopyx.com
License: UNKNOWN
Keywords: Python Produce & Publish
Platform: UNKNOWN
Classifier: Programming Language :: Python
Classifier: Programming Language :: Python :: 2.7
Classifier: Programming Language :: Python :: 3.6
Classifier: Programming Language :: Python :: 3.7
